{
    "behavior": "",
    "checkable": false,
    "class": "button",
    "clickable": true,
    "content-desc": "",
    "enabled": true,
    "focusable": true,
    "focused": false,
    "hash": "xdkdoObmonTO6PEwwgTkzg==\n",
    "height": 34,
    "hier_level": 0,
    "human_hash": "button_X1834_Y1_W38_H34",
    "internal": {
        "elem_dict": {
            "attributes": {
                "class": "nav-btn p0-sm d-sm-b body-4 u-bold ml2-sm mr2-sm",
                "data-path": "sign in",
                "data-pre": "ILink",
                "data-type": "click_navMembership",
                "data-var": "loginBtn"
            },
            "backend_node_id": 595,
            "flags": {
                "checkable": false,
                "clickable": true,
                "enabled": true,
                "focusable": true,
                "focused": false,
                "scrollable": false
            },
            "height": 34.0,
            "key": "1834_1_38_34_Sign In",
            "tagName": "button",
            "text": "Sign In",
            "width": 38.0,
            "x": 1834.0,
            "y": 1.0
        },
        "location": {
            "x": 1834.0,
            "y": 1.0
        },
        "size": {
            "height": 34.0,
            "width": 38.0
        },
        "tag_name": "button",
        "text": "Sign In"
    },
    "is_transformed": true,
    "package": "",
    "password": false,
    "resource-id": "",
    "scrollable": false,
    "tag_name": "button",
    "text": "Sign In",
    "transformed": true,
    "width": 38,
    "x": 1834,
    "y": 1
}